aisdc/__init__.py
aisdc/main.py
aisdc/metrics.py
aisdc/attacks/__init__.py
aisdc/attacks/attack.py
aisdc/attacks/attack_report_formatter.py
aisdc/attacks/attribute_attack.py
aisdc/attacks/factory.py
aisdc/attacks/likelihood_attack.py
aisdc/attacks/report.py
aisdc/attacks/structural_attack.py
aisdc/attacks/target.py
aisdc/attacks/worst_case_attack.py
aisdc/config/__init__.py
aisdc/config/attack.py
aisdc/config/target.py
aisdc/config/utils.py
aisdc/preprocessing/__init__.py
aisdc/preprocessing/loaders.py
aisdc/safemodel/__init__.py
aisdc/safemodel/reporting.py
aisdc/safemodel/rules.json
aisdc/safemodel/safemodel.py
aisdc/safemodel/classifiers/__init__.py
aisdc/safemodel/classifiers/dp_svc.py
aisdc/safemodel/classifiers/new_model_template.py
aisdc/safemodel/classifiers/safedecisiontreeclassifier.py
aisdc/safemodel/classifiers/safekeras.py
aisdc/safemodel/classifiers/saferandomforestclassifier.py
aisdc/safemodel/classifiers/safesvc.py
aisdc/safemodel/classifiers/safetf.py
aisdc-1.2.0.dist-info/METADATA
aisdc-1.2.0.dist-info/WHEEL
aisdc-1.2.0.dist-info/entry_points.txt
aisdc-1.2.0.dist-info/top_level.txt
aisdc-1.2.0.dist-info/RECORD
