Metadata-Version: 2.1
Name: aisdc
Version: 1.2.0
Summary: Tools for the statistical disclosure control of machine learning models
Home-page: https://github.com/AI-SDC/AI-SDC
Maintainer: Jim Smith
Maintainer-email: james.smith@uwe.ac.uk
License: MIT
Project-URL: Changelog, https://github.com/AI-SDC/AI-SDC/CHANGELOG.md
Project-URL: Documentation, https://ai-sdc.github.io/AI-SDC/
Project-URL: Bug Tracker, https://github.com/AI-SDC/AI-SDC/issues
Project-URL: Discussions, https://github.com/AI-SDC/AI-SDC/discussions
Keywords: data-privacy,data-protection,machine-learning,privacy,privacy-tools,statistical-disclosure-control
Classifier: Development Status :: 5 - Production/Stable
Classifier: Intended Audience :: Developers
Classifier: Intended Audience :: Science/Research
Classifier: License :: OSI Approved :: MIT License
Classifier: Natural Language :: English
Classifier: Programming Language :: Python :: 3.9
Classifier: Programming Language :: Python :: 3.10
Classifier: Programming Language :: Python :: 3.11
Classifier: Topic :: Scientific/Engineering
Classifier: Topic :: Scientific/Engineering :: Artificial Intelligence
Classifier: Topic :: Scientific/Engineering :: Information Analysis
Classifier: Operating System :: OS Independent
Requires-Python: <3.12,>=3.9
Requires-Dist: acro ==0.4.6
Requires-Dist: fpdf
Requires-Dist: pypdf
Requires-Dist: multiprocess
Requires-Dist: scikit-learn
Requires-Dist: xgboost
Provides-Extra: doc
Requires-Dist: tensorflow <2.15,>=2.14 ; extra == 'doc'
Requires-Dist: tensorflow-privacy ==0.9.0 ; extra == 'doc'
Requires-Dist: dictdiffer ; extra == 'doc'
Requires-Dist: numpydoc ; extra == 'doc'
Requires-Dist: sphinx-autopackagesummary ; extra == 'doc'
Requires-Dist: sphinx-issues ; extra == 'doc'
Requires-Dist: sphinx-prompt ; extra == 'doc'
Requires-Dist: sphinx-rtd-theme ; extra == 'doc'
Requires-Dist: sphinx ; extra == 'doc'
Provides-Extra: safemodel
Requires-Dist: tensorflow <2.15,>=2.14 ; extra == 'safemodel'
Requires-Dist: tensorflow-privacy ==0.9.0 ; extra == 'safemodel'
Requires-Dist: dictdiffer ; extra == 'safemodel'
Provides-Extra: test
Requires-Dist: tensorflow <2.15,>=2.14 ; extra == 'test'
Requires-Dist: tensorflow-privacy ==0.9.0 ; extra == 'test'
Requires-Dist: dictdiffer ; extra == 'test'
Requires-Dist: pytest ; extra == 'test'
Requires-Dist: pytest-cov ; extra == 'test'
